mtrequests/__init__.py
mtrequests/pending_pool.py
mtrequests/pending_request.py
mtrequests/pending_response.py
mtrequests/request.py
mtrequests/request_hook.py
mtrequests/session.py
mtrequests/utils.py
mtrequests-2.1.1.dist-info/LICENSE
mtrequests-2.1.1.dist-info/METADATA
mtrequests-2.1.1.dist-info/WHEEL
mtrequests-2.1.1.dist-info/top_level.txt
mtrequests-2.1.1.dist-info/RECORD
