Metadata-Version: 2.1
Name: mtrequests
Version: 2.1.1
Summary: threading for requests
Home-page: https://github.com/dail45/mtrequests
Author: dail45
Keywords: requests threading
Classifier: Programming Language :: Python :: 3.11
Classifier: License :: OSI Approved :: MIT License
Classifier: Operating System :: OS Independent
Requires: requests
Requires: tls_client
Requires-Python: >=3.6
License-File: LICENSE
Requires-Dist: requests
Requires-Dist: tls-client
